MANIFEST.in
README.rst
requirements.txt
setup.cfg
setup.py
djmicrosip_reportes/__init__.py
djmicrosip_reportes/__init__.pyc
djmicrosip_reportes/autocomplete_light_registry.pyc
djmicrosip_reportes/config.pyc
djmicrosip_reportes/forms.pyc
djmicrosip_reportes/models.pyc
djmicrosip_reportes/urls.pyc
djmicrosip_reportes/views.pyc
djmicrosip_reportes.egg-info/PKG-INFO
djmicrosip_reportes.egg-info/SOURCES.txt
djmicrosip_reportes.egg-info/dependency_links.txt
djmicrosip_reportes.egg-info/top_level.txt
djmicrosip_reportes/templates/djmicrosip_reportes/base.html
djmicrosip_reportes/templates/djmicrosip_reportes/existencia_linea.html
djmicrosip_reportes/templates/djmicrosip_reportes/index.html
djmicrosip_reportes/templates/djmicrosip_reportes/reporte_inv_x_lote.html